Comparador/comparador.vhd
Library IEEE;
use IEEE.std_logic_1164.all;

Entity comparador is
    port(
        A, B, Gi, Ei, Li : in  std_logic;
        Go, Eo, Lo       : out std_logic
    );
End comparador;

Architecture comparation of comparador is
    begin
        Go <= Gi or ( Ei AND (A AND NOT(B))); -- Mayor
        Eo <= Ei AND (A XNOR B);              -- Igual
        Lo <= Li or (Ei AND (NOT(A) AND B));  -- Menor
END comparation;

Comparador/TB_comparador.vhd
Library IEEE;
use IEEE.std_logic_1164.all;

Entity TB_comparador is
End TB_comparador;

architecture simulation of TB_comparador is
    component comparador is
        port(
            A, B, Gi, Ei, Li : in  std_logic;
            Go, Eo, Lo       : out std_logic
        );
    End component;
    
    signal A, B, Go, Eo, Lo, Gi, Li, Ei : std_logic;
    begin
        SIMBLK : comparador PORT MAP(A,B,Gi,Ei,Li,Go,Eo,Lo);
        process
        begin
        --
        Gi <= '1';
        Ei <= '0';
        Li <= '0';
        A <= '0';
        B <= '0';
        wait for 20 ns;
        --
        Gi <= '1';
        Ei <= '0';
        Li <= '0';
        A <= '1';
        B <= '0';
        wait for 20 ns;
        --
        Gi <= '1';
        Ei <= '0';
        Li <= '0';
        A <= '0';
        B <= '1';
        wait for 20 ns;
        --
        Gi <= '0';
        Ei <= '0';
        Li <= '1';
        A <= '0';
        B <= '0';
        wait for 20 ns;
         --
         Gi <= '0';
         Ei <= '0';
         Li <= '1';
         A <= '1';
         B <= '0';
         wait for 20 ns;
          --
        Gi <= '0';
        Ei <= '0';
        Li <= '1';
        A <= '0';
        B <= '1';
        wait for 20 ns;

         --
         Gi <= '0';
         Ei <= '1';
         Li <= '0';
         A <= '0';
         B <= '0';
         wait for 20 ns;
        --
        Gi <= '0';
        Ei <= '1';
        Li <= '0';
        A <= '0';
        B <= '0';
        wait for 20 ns;
        --
        Gi <= '0';
        Ei <= '1';
        Li <= '0';
        A <= '0';
        B <= '1';
        wait for 20 ns;
        --
        Gi <= '0';
        Ei <= '1';
        Li <= '0';
        A <= '1';
        B <= '0';
        wait for 20 ns;
        --
        Gi <= '0';
        Ei <= '1';
        Li <= '0';
        A <= '1';
        B <= '1';
        wait for 20 ns;
        end process;
end simulation;

Comparador/Comparador.vcd
$date
  Thu Jul 14 17:19:45 2022
$end
$version
  GHDL v0
$end
$timescale
  1 fs
$end
$scope module standard $end
$upscope $end
$scope module std_logic_1164 $end
$upscope $end
$scope module tb_comparador $end
$var reg 1 ! a $end
$var reg 1 " b $end
$var reg 1 # go $end
$var reg 1 $ eo $end
$var reg 1 % lo $end
$var reg 1 & gi $end
$var reg 1 ' li $end
$var reg 1 ( ei $end
$scope module simblk $end
$var reg 1 ) a $end
$var reg 1 * b $end
$var reg 1 + gi $end
$var reg 1 , ei $end
$var reg 1 - li $end
$var reg 1 . go $end
$var reg 1 / eo $end
$var reg 1 0 lo $end
$upscope $end
$upscope $end
$enddefinitions $end
#0
0!
0"
1#
0$
0%
1&
0'
0(
0)
0*
1+
0,
0-
1.
0/
00
#20000000
1!
1)
#40000000
0!
1"
0)
1*
#60000000
0"
0#
1%
0&
1'
0*
0+
1-
0.
10
#80000000
1!
1)
#100000000
0!
1"
0)
1*
#120000000
0"
1$
0%
0'
1(
0*
1,
0-
1/
00
#140000000
#160000000
1"
0$
1%
1*
0/
10
#180000000
1!
0"
1#
0%
1)
0*
1.
00
#200000000
1"
0#
1$
1*
0.
1/
#220000000
0!
0"
1#
0$
1&
0(
0)
0*
1+
0,
1.
0/
#240000000
1!
1)
