Sumador/sumador.vhd
LIBRARY IEEE;
USE IEEE.std_logic_1164.all;

Entity sumador is 
    port(
        A  : in  std_logic;
        B  : in  std_logic;
        Ci : in  std_logic;
        S  : out std_logic;
        Co : out std_logic);
End sumador;

Architecture Behavioral of sumador is
    begin
        S  <= (A XOR B) XOR Ci;
        Co <= (A AND B) OR (A AND CI) OR (B AND CI);
End Behavioral;

Sumador/TB_sumador.vhd
LIBRARY IEEE;
USE IEEE.std_logic_1164.all;

Entity TB_sumador is 
End TB_sumador;

Architecture simulation of TB_sumador is
    component sumador is 
        port(
            A  : in  std_logic;
            B  : in  std_logic;
            Ci : in  std_logic;
            S  : out std_logic;
            Co : out std_logic);
    end component;

    signal A, B, Ci, Co, S : std_logic;
    begin
        SIMBLK01 : sumador PORT MAP(A, B, Ci, S, Co);
        process
        begin   
            --
            Ci <= '0';
            A <= '0';
            B <= '0';
            wait for 20 ns;
            --
            Ci <= '0';
            A <= '0';
            B <= '1';
            wait for 20 ns;
            --
            Ci <= '0';
            A <= '1';
            B <= '0';
            wait for 20 ns;
            --
            Ci <= '0';
            A <= '1';
            B <= '1';
            wait for 20 ns;
            --
            Ci <= '1';
            A <= '0';
            B <= '0';
            wait for 20 ns;
            --
            Ci <= '1';
            A <= '0';
            B <= '1';
            wait for 20 ns;
            --
            Ci <= '1';
            A <= '1';
            B <= '0';
            wait for 20 ns;
            --
            Ci <= '1';
            A <= '1';
            B <= '1';
            wait;
        end process;
End simulation;

Sumador/BCD7SEG.vcd
$date
  Thu Nov 17 16:59:34 2022
$end
$version
  GHDL v0
$end
$timescale
  1 fs
$end
$scope module standard $end
$upscope $end
$scope module std_logic_1164 $end
$upscope $end
$scope module tb_sumador $end
$var reg 1 ! a $end
$var reg 1 " b $end
$var reg 1 # ci $end
$var reg 1 $ co $end
$var reg 1 % s $end
$scope module simblk01 $end
$var reg 1 & a $end
$var reg 1 ' b $end
$var reg 1 ( ci $end
$var reg 1 ) s $end
$var reg 1 * co $end
$upscope $end
$upscope $end
$enddefinitions $end
#0
0!
0"
0#
0$
0%
0&
0'
0(
0)
0*
#20000000
1"
1%
1'
1)
#40000000
1!
0"
1&
0'
#60000000
1"
1$
0%
1'
0)
1*
#80000000
0!
0"
1#
0$
1%
0&
0'
1(
1)
0*
#100000000
1"
1$
0%
1'
0)
1*
#120000000
1!
0"
1&
0'
#140000000
1"
1%
1'
1)
