MUX_4_1/MUX_4_1.vhd
LIBRARY IEEE;
USE IEEE.std_logic_1164.all;

Entity MUX_4_1 is
    port(
        X0 : in std_logic;      -- Entrada 0 del multiplexor
        X1 : in std_logic;
        X2 : in std_logic;
        X3 : in std_logic;
        S  : in std_logic_vector(1 downto 0);
        Y0 : out std_logic);
END MUX_4_1;

Architecture Simple of MUX_4_1 is
Begin
    Y0 <= (X0 AND NOT S(1) and NOT S(0)) OR ((X1 AND NOT S(1) and S(0))) or ((X2 AND S(1) and NOT S(0))) or ((X3 AND S(0) and S(1)));
End Simple;

MUX_4_1/TB_MUX_4_1.vhd
LIBRARY IEEE;
USE IEEE.std_logic_1164.all;

Entity TB_MUX_4_1 is

END TB_MUX_4_1;

Architecture Simulation of TB_MUX_4_1 is
    Component MUX_4_1 
    port(
        X0 : in std_logic;      -- Entrada 0 del multiplexor
        X1 : in std_logic;
        X2 : in std_logic;
        X3 : in std_logic;
        S  : in std_logic_vector(1 downto 0);
        Y0 : out std_logic);
    End Component;

    signal X0, X1, X2, X3, Y0 : std_logic;
    signal S : std_logic_vector(1 downto 0);
    begin
        SimBLk : MUX_4_1 PORT MAP(X0, X1, X2, X3,S,Y0);

        process
        begin
            --
            X0 <= '0';
            X1 <= '0';
            X2 <= '0';
            X3 <= '0';
            S <= "00";
            wait for 20 ns;
            --
            X0 <= '1';
            X1 <= '0';
            X2 <= '0';
            X3 <= '0';
            S <= "00";
            wait for 20 ns;
            --
            X0 <= '0';
            X1 <= '1';
            X2 <= '0';
            X3 <= '0';
            S <= "00";
            wait for 20 ns;
            --
            X0 <= '0';
            X1 <= '1';
            X2 <= '0';
            X3 <= '0';
            S <= "01";
            wait for 20 ns;
            --
            X0 <= '0';
            X1 <= '0';
            X2 <= '0';
            X3 <= '0';
            S <= "01";
            wait for 20 ns;
            --
            X0 <= '0';
            X1 <= '0';
            X2 <= '1';
            X3 <= '0';
            S <= "10";
            wait for 20 ns;
            --
            X0 <= '0';
            X1 <= '0';
            X2 <= '0';
            X3 <= '0';
            S <= "10";
            wait for 20 ns;
            --
            X0 <= '0';
            X1 <= '0';
            X2 <= '0';
            X3 <= '1';
            S <= "11";
            wait for 20 ns;
            --
            X0 <= '0';
            X1 <= '0';
            X2 <= '0';
            X3 <= '0';
            S <= "11";
            wait;
            --
        end process;
    end Simulation;

MUX_4_1/MUX_4_1.vcd
$date
  Thu Nov 10 16:39:00 2022
$end
$version
  GHDL v0
$end
$timescale
  1 fs
$end
$scope module standard $end
$upscope $end
$scope module std_logic_1164 $end
$upscope $end
$scope module tb_mux_4_1 $end
$var reg 1 ! x0 $end
$var reg 1 " x1 $end
$var reg 1 # x2 $end
$var reg 1 $ x3 $end
$var reg 1 % y0 $end
$var reg 2 & s[1:0] $end
$scope module simblk $end
$var reg 1 ' x0 $end
$var reg 1 ( x1 $end
$var reg 1 ) x2 $end
$var reg 1 * x3 $end
$var reg 2 + s[1:0] $end
$var reg 1 , y0 $end
$upscope $end
$upscope $end
$enddefinitions $end
#0
0!
0"
0#
0$
0%
b00 &
0'
0(
0)
0*
b00 +
0,
#20000000
1!
1%
1'
1,
#40000000
0!
1"
0%
0'
1(
0,
#60000000
1%
b01 &
b01 +
1,
#80000000
0"
0%
0(
0,
#100000000
1#
1%
b10 &
1)
b10 +
1,
#120000000
0#
0%
0)
0,
#140000000
1$
1%
b11 &
1*
b11 +
1,
#160000000
0$
0%
0*
0,
